tidyplot/__init__.py
tidyplot/model_selection.py
tidyplot-0.0.4.dist-info/LICENSE
tidyplot-0.0.4.dist-info/METADATA
tidyplot-0.0.4.dist-info/WHEEL
tidyplot-0.0.4.dist-info/top_level.txt
tidyplot-0.0.4.dist-info/RECORD
