Metadata-Version: 2.1
Name: tidyplot
Version: 0.0.4
Summary: a plot tool
Home-page: https://github.com/aierwiki/tidyplot
Author: Tang Yubin
Author-email: tang-yu-bin@qq.com
License: UNKNOWN
Platform: UNKNOWN
Classifier: Programming Language :: Python :: 3
Classifier: License :: OSI Approved :: MIT License
Classifier: Operating System :: OS Independent
